{
    "best deployment": "combination_10",
    "schedule file": "model_schedules_3model_rs_rb_ys_4.yaml",
    "data": [
        {
            "timestamp": "2025-09-08 04:53:30",
            "window_sec": 10.0,
            "combination": "combination_1",
            "models": {
                "view1": {
                    "model": "resnet50_big",
                    "execution": "CPU",
                    "throughput_fps": 4.81,
                    "avg_inference_time_ms": 208.0,
                    "inference_count": 48,
                    "avg_wait_to_preprocess_ms": 0.0,
                    "dropped_frames_due_to_full_queue": 0
                },
                "view2": {
                    "model": "resnet50_small",
                    "execution": "CPU",
                    "throughput_fps": 5.92,
                    "avg_inference_time_ms": 168.88,
                    "inference_count": 59,
                    "avg_wait_to_preprocess_ms": 0.0,
                    "dropped_frames_due_to_full_queue": 0
                },
                "view3": {
                    "model": "yolov3_small",
                    "execution": "CPU",
                    "throughput_fps": 0.91,
                    "avg_inference_time_ms": 1102.93,
                    "inference_count": 8,
                    "avg_wait_to_preprocess_ms": 5316.99,
                    "dropped_frames_due_to_full_queue": 260
                }
            },
            "total": {
                "total_throughput_fps": 11.64,
                "avg_throughput_fps": 3.88
            },
            "devices": {
                "cpu": {
                    "queue_wait_ms_p95": 5316.99
                }
            },
            "derived": {
                "drop_rate_fps": 26.0,
                "drop_count": 260,
                "window_sec": 10.0
            },
            "score": 6.44
        },
        {
            "timestamp": "2025-09-08 04:53:41",
            "window_sec": 10.0,
            "combination": "combination_10",
            "models": {
                "view1": {
                    "model": "resnet50_big",
                    "execution": "NPU0",
                    "throughput_fps": 21.49,
                    "avg_inference_time_ms": 46.53,
                    "inference_count": 95,
                    "avg_wait_to_preprocess_ms": 0.0,
                    "dropped_frames_due_to_full_queue": 0
                },
                "view2": {
                    "model": "resnet50_small",
                    "execution": "NPU1",
                    "throughput_fps": 21.18,
                    "avg_inference_time_ms": 47.22,
                    "inference_count": 95,
                    "avg_wait_to_preprocess_ms": 0.0,
                    "dropped_frames_due_to_full_queue": 0
                },
                "view3": {
                    "model": "yolov3_small",
                    "execution": "CPU",
                    "throughput_fps": 3.27,
                    "avg_inference_time_ms": 305.48,
                    "inference_count": 28,
                    "avg_wait_to_preprocess_ms": 2795.56,
                    "dropped_frames_due_to_full_queue": 228
                }
            },
            "total": {
                "total_throughput_fps": 45.94,
                "avg_throughput_fps": 15.31
            },
            "devices": {
                "cpu": {
                    "queue_wait_ms_p95": 2795.56
                },
                "npu0": {
                    "queue_wait_ms_p95": 0.0,
                    "t_preload_ms": 33.52
                },
                "npu1": {
                    "queue_wait_ms_p95": 0.0,
                    "t_preload_ms": 464.87
                }
            },
            "derived": {
                "drop_rate_fps": 22.8,
                "drop_count": 228,
                "window_sec": 10.0
            },
            "score": 41.38
        },
        {
            "timestamp": "2025-09-08 04:53:52",
            "window_sec": 10.0,
            "combination": "combination_11",
            "models": {
                "view1": {
                    "model": "resnet50_big",
                    "execution": "NPU1",
                    "throughput_fps": 20.64,
                    "avg_inference_time_ms": 48.46,
                    "inference_count": 94,
                    "avg_wait_to_preprocess_ms": 0.0,
                    "dropped_frames_due_to_full_queue": 0
                },
                "view2": {
                    "model": "resnet50_small",
                    "execution": "CPU",
                    "throughput_fps": 7.15,
                    "avg_inference_time_ms": 139.81,
                    "inference_count": 64,
                    "avg_wait_to_preprocess_ms": 0.0,
                    "dropped_frames_due_to_full_queue": 0
                },
                "view3": {
                    "model": "yolov3_small",
                    "execution": "CPU",
                    "throughput_fps": 1.31,
                    "avg_inference_time_ms": 764.75,
                    "inference_count": 11,
                    "avg_wait_to_preprocess_ms": 5143.16,
                    "dropped_frames_due_to_full_queue": 236
                }
            },
            "total": {
                "total_throughput_fps": 29.1,
                "avg_throughput_fps": 9.7
            },
            "devices": {
                "cpu": {
                    "queue_wait_ms_p95": 5143.16
                },
                "npu1": {
                    "queue_wait_ms_p95": 0.0,
                    "t_preload_ms": 464.87
                }
            },
            "derived": {
                "drop_rate_fps": 23.6,
                "drop_count": 236,
                "window_sec": 10.0
            },
            "score": 24.38
        },
        {
            "timestamp": "2025-09-08 04:54:03",
            "window_sec": 10.0,
            "combination": "combination_12",
            "models": {
                "view1": {
                    "model": "resnet50_big",
                    "execution": "NPU1",
                    "throughput_fps": 20.1,
                    "avg_inference_time_ms": 49.74,
                    "inference_count": 94,
                    "avg_wait_to_preprocess_ms": 0.0,
                    "dropped_frames_due_to_full_queue": 0
                },
                "view2": {
                    "model": "resnet50_small",
                    "execution": "CPU",
                    "throughput_fps": 9.1,
                    "avg_inference_time_ms": 109.86,
                    "inference_count": 82,
                    "avg_wait_to_preprocess_ms": 0.0,
                    "dropped_frames_due_to_full_queue": 0
                },
                "view3": {
                    "model": "yolov3_small",
                    "execution": "NPU0",
                    "throughput_fps": 10.31,
                    "avg_inference_time_ms": 96.98,
                    "inference_count": 31,
                    "avg_wait_to_preprocess_ms": 1390.78,
                    "dropped_frames_due_to_full_queue": 187
                }
            },
            "total": {
                "total_throughput_fps": 39.52,
                "avg_throughput_fps": 13.17
            },
            "devices": {
                "cpu": {
                    "queue_wait_ms_p95": 0.0
                },
                "npu0": {
                    "queue_wait_ms_p95": 0.0,
                    "t_preload_ms": 33.52
                },
                "npu1": {
                    "queue_wait_ms_p95": 0.0,
                    "t_preload_ms": 464.87
                }
            },
            "derived": {
                "drop_rate_fps": 18.7,
                "drop_count": 187,
                "window_sec": 10.0
            },
            "score": 35.78
        },
        {
            "timestamp": "2025-09-08 04:54:14",
            "window_sec": 10.0,
            "combination": "combination_13",
            "models": {
                "view1": {
                    "model": "resnet50_big",
                    "execution": "NPU1",
                    "throughput_fps": 20.95,
                    "avg_inference_time_ms": 47.73,
                    "inference_count": 95,
                    "avg_wait_to_preprocess_ms": 0.0,
                    "dropped_frames_due_to_full_queue": 0
                },
                "view2": {
                    "model": "resnet50_small",
                    "execution": "NPU0",
                    "throughput_fps": 21.07,
                    "avg_inference_time_ms": 47.45,
                    "inference_count": 95,
                    "avg_wait_to_preprocess_ms": 0.0,
                    "dropped_frames_due_to_full_queue": 0
                },
                "view3": {
                    "model": "yolov3_small",
                    "execution": "CPU",
                    "throughput_fps": 2.9,
                    "avg_inference_time_ms": 345.06,
                    "inference_count": 24,
                    "avg_wait_to_preprocess_ms": 3066.57,
                    "dropped_frames_due_to_full_queue": 230
                }
            },
            "total": {
                "total_throughput_fps": 44.92,
                "avg_throughput_fps": 14.97
            },
            "devices": {
                "cpu": {
                    "queue_wait_ms_p95": 3066.57
                },
                "npu0": {
                    "queue_wait_ms_p95": 0.0,
                    "t_preload_ms": 33.52
                },
                "npu1": {
                    "queue_wait_ms_p95": 0.0,
                    "t_preload_ms": 464.87
                }
            },
            "derived": {
                "drop_rate_fps": 23.0,
                "drop_count": 230,
                "window_sec": 10.0
            },
            "score": 40.32
        },
        {
            "timestamp": "2025-09-08 04:54:25",
            "window_sec": 10.0,
            "combination": "combination_2",
            "models": {
                "view1": {
                    "model": "resnet50_big",
                    "execution": "CPU",
                    "throughput_fps": 5.02,
                    "avg_inference_time_ms": 199.21,
                    "inference_count": 46,
                    "avg_wait_to_preprocess_ms": 0.0,
                    "dropped_frames_due_to_full_queue": 0
                },
                "view2": {
                    "model": "resnet50_small",
                    "execution": "CPU",
                    "throughput_fps": 5.64,
                    "avg_inference_time_ms": 177.38,
                    "inference_count": 51,
                    "avg_wait_to_preprocess_ms": 0.0,
                    "dropped_frames_due_to_full_queue": 0
                },
                "view3": {
                    "model": "yolov3_small",
                    "execution": "NPU0",
                    "throughput_fps": 10.76,
                    "avg_inference_time_ms": 92.93,
                    "inference_count": 29,
                    "avg_wait_to_preprocess_ms": 1509.77,
                    "dropped_frames_due_to_full_queue": 192
                }
            },
            "total": {
                "total_throughput_fps": 21.42,
                "avg_throughput_fps": 7.14
            },
            "devices": {
                "cpu": {
                    "queue_wait_ms_p95": 0.0
                },
                "npu0": {
                    "queue_wait_ms_p95": 0.0,
                    "t_preload_ms": 33.52
                }
            },
            "derived": {
                "drop_rate_fps": 19.2,
                "drop_count": 192,
                "window_sec": 10.0
            },
            "score": 17.58
        },
        {
            "timestamp": "2025-09-08 04:54:36",
            "window_sec": 10.0,
            "combination": "combination_3",
            "models": {
                "view1": {
                    "model": "resnet50_big",
                    "execution": "CPU",
                    "throughput_fps": 5.31,
                    "avg_inference_time_ms": 188.49,
                    "inference_count": 48,
                    "avg_wait_to_preprocess_ms": 0.0,
                    "dropped_frames_due_to_full_queue": 0
                },
                "view2": {
                    "model": "resnet50_small",
                    "execution": "CPU",
                    "throughput_fps": 4.71,
                    "avg_inference_time_ms": 212.46,
                    "inference_count": 42,
                    "avg_wait_to_preprocess_ms": 0.0,
                    "dropped_frames_due_to_full_queue": 0
                },
                "view3": {
                    "model": "yolov3_small",
                    "execution": "NPU1",
                    "throughput_fps": 9.53,
                    "avg_inference_time_ms": 104.91,
                    "inference_count": 27,
                    "avg_wait_to_preprocess_ms": 1613.16,
                    "dropped_frames_due_to_full_queue": 192
                }
            },
            "total": {
                "total_throughput_fps": 19.54,
                "avg_throughput_fps": 6.51
            },
            "devices": {
                "cpu": {
                    "queue_wait_ms_p95": 0.0
                },
                "npu1": {
                    "queue_wait_ms_p95": 0.0,
                    "t_preload_ms": 464.87
                }
            },
            "derived": {
                "drop_rate_fps": 19.2,
                "drop_count": 192,
                "window_sec": 10.0
            },
            "score": 15.7
        },
        {
            "timestamp": "2025-09-08 04:54:47",
            "window_sec": 10.0,
            "combination": "combination_4",
            "models": {
                "view1": {
                    "model": "resnet50_big",
                    "execution": "CPU",
                    "throughput_fps": 7.08,
                    "avg_inference_time_ms": 141.21,
                    "inference_count": 64,
                    "avg_wait_to_preprocess_ms": 0.0,
                    "dropped_frames_due_to_full_queue": 0
                },
                "view2": {
                    "model": "resnet50_small",
                    "execution": "NPU0",
                    "throughput_fps": 19.66,
                    "avg_inference_time_ms": 50.87,
                    "inference_count": 92,
                    "avg_wait_to_preprocess_ms": 0.0,
                    "dropped_frames_due_to_full_queue": 0
                },
                "view3": {
                    "model": "yolov3_small",
                    "execution": "CPU",
                    "throughput_fps": 1.11,
                    "avg_inference_time_ms": 902.01,
                    "inference_count": 9,
                    "avg_wait_to_preprocess_ms": 4895.29,
                    "dropped_frames_due_to_full_queue": 224
                }
            },
            "total": {
                "total_throughput_fps": 27.85,
                "avg_throughput_fps": 9.28
            },
            "devices": {
                "cpu": {
                    "queue_wait_ms_p95": 4895.29
                },
                "npu0": {
                    "queue_wait_ms_p95": 0.0,
                    "t_preload_ms": 33.52
                }
            },
            "derived": {
                "drop_rate_fps": 22.4,
                "drop_count": 224,
                "window_sec": 10.0
            },
            "score": 23.37
        },
        {
            "timestamp": "2025-09-08 04:54:58",
            "window_sec": 10.0,
            "combination": "combination_5",
            "models": {
                "view1": {
                    "model": "resnet50_big",
                    "execution": "CPU",
                    "throughput_fps": 9.13,
                    "avg_inference_time_ms": 109.47,
                    "inference_count": 82,
                    "avg_wait_to_preprocess_ms": 0.0,
                    "dropped_frames_due_to_full_queue": 0
                },
                "view2": {
                    "model": "resnet50_small",
                    "execution": "NPU0",
                    "throughput_fps": 20.7,
                    "avg_inference_time_ms": 48.32,
                    "inference_count": 93,
                    "avg_wait_to_preprocess_ms": 0.0,
                    "dropped_frames_due_to_full_queue": 0
                },
                "view3": {
                    "model": "yolov3_small",
                    "execution": "NPU1",
                    "throughput_fps": 9.29,
                    "avg_inference_time_ms": 107.65,
                    "inference_count": 28,
                    "avg_wait_to_preprocess_ms": 1548.07,
                    "dropped_frames_due_to_full_queue": 142
                }
            },
            "total": {
                "total_throughput_fps": 39.12,
                "avg_throughput_fps": 13.04
            },
            "devices": {
                "cpu": {
                    "queue_wait_ms_p95": 0.0
                },
                "npu0": {
                    "queue_wait_ms_p95": 0.0,
                    "t_preload_ms": 33.52
                },
                "npu1": {
                    "queue_wait_ms_p95": 0.0,
                    "t_preload_ms": 464.87
                }
            },
            "derived": {
                "drop_rate_fps": 14.2,
                "drop_count": 142,
                "window_sec": 10.0
            },
            "score": 36.28
        },
        {
            "timestamp": "2025-09-08 04:55:10",
            "window_sec": 10.0,
            "combination": "combination_6",
            "models": {
                "view1": {
                    "model": "resnet50_big",
                    "execution": "CPU",
                    "throughput_fps": 7.82,
                    "avg_inference_time_ms": 127.95,
                    "inference_count": 70,
                    "avg_wait_to_preprocess_ms": 0.0,
                    "dropped_frames_due_to_full_queue": 0
                },
                "view2": {
                    "model": "resnet50_small",
                    "execution": "NPU1",
                    "throughput_fps": 19.89,
                    "avg_inference_time_ms": 50.29,
                    "inference_count": 92,
                    "avg_wait_to_preprocess_ms": 0.0,
                    "dropped_frames_due_to_full_queue": 0
                },
                "view3": {
                    "model": "yolov3_small",
                    "execution": "CPU",
                    "throughput_fps": 1.16,
                    "avg_inference_time_ms": 860.64,
                    "inference_count": 9,
                    "avg_wait_to_preprocess_ms": 5703.83,
                    "dropped_frames_due_to_full_queue": 166
                }
            },
            "total": {
                "total_throughput_fps": 28.86,
                "avg_throughput_fps": 9.62
            },
            "devices": {
                "cpu": {
                    "queue_wait_ms_p95": 5703.83
                },
                "npu1": {
                    "queue_wait_ms_p95": 0.0,
                    "t_preload_ms": 464.87
                }
            },
            "derived": {
                "drop_rate_fps": 16.6,
                "drop_count": 166,
                "window_sec": 10.0
            },
            "score": 25.54
        },
        {
            "timestamp": "2025-09-08 04:55:20",
            "window_sec": 10.0,
            "combination": "combination_7",
            "models": {
                "view1": {
                    "model": "resnet50_big",
                    "execution": "CPU",
                    "throughput_fps": 8.69,
                    "avg_inference_time_ms": 115.06,
                    "inference_count": 79,
                    "avg_wait_to_preprocess_ms": 0.0,
                    "dropped_frames_due_to_full_queue": 0
                },
                "view2": {
                    "model": "resnet50_small",
                    "execution": "NPU1",
                    "throughput_fps": 19.85,
                    "avg_inference_time_ms": 50.37,
                    "inference_count": 91,
                    "avg_wait_to_preprocess_ms": 0.0,
                    "dropped_frames_due_to_full_queue": 0
                },
                "view3": {
                    "model": "yolov3_small",
                    "execution": "NPU0",
                    "throughput_fps": 10.09,
                    "avg_inference_time_ms": 99.08,
                    "inference_count": 29,
                    "avg_wait_to_preprocess_ms": 1472.65,
                    "dropped_frames_due_to_full_queue": 86
                }
            },
            "total": {
                "total_throughput_fps": 38.64,
                "avg_throughput_fps": 12.88
            },
            "devices": {
                "cpu": {
                    "queue_wait_ms_p95": 0.0
                },
                "npu0": {
                    "queue_wait_ms_p95": 0.0,
                    "t_preload_ms": 33.52
                },
                "npu1": {
                    "queue_wait_ms_p95": 0.0,
                    "t_preload_ms": 464.87
                }
            },
            "derived": {
                "drop_rate_fps": 8.6,
                "drop_count": 86,
                "window_sec": 10.0
            },
            "score": 36.92
        },
        {
            "timestamp": "2025-09-08 04:55:31",
            "window_sec": 10.0,
            "combination": "combination_8",
            "models": {
                "view1": {
                    "model": "resnet50_big",
                    "execution": "NPU0",
                    "throughput_fps": 19.88,
                    "avg_inference_time_ms": 50.3,
                    "inference_count": 89,
                    "avg_wait_to_preprocess_ms": 0.0,
                    "dropped_frames_due_to_full_queue": 0
                },
                "view2": {
                    "model": "resnet50_small",
                    "execution": "CPU",
                    "throughput_fps": 6.68,
                    "avg_inference_time_ms": 149.69,
                    "inference_count": 60,
                    "avg_wait_to_preprocess_ms": 0.0,
                    "dropped_frames_due_to_full_queue": 0
                },
                "view3": {
                    "model": "yolov3_small",
                    "execution": "CPU",
                    "throughput_fps": 0.99,
                    "avg_inference_time_ms": 1008.85,
                    "inference_count": 8,
                    "avg_wait_to_preprocess_ms": 5176.38,
                    "dropped_frames_due_to_full_queue": 144
                }
            },
            "total": {
                "total_throughput_fps": 27.55,
                "avg_throughput_fps": 9.18
            },
            "devices": {
                "cpu": {
                    "queue_wait_ms_p95": 5176.38
                },
                "npu0": {
                    "queue_wait_ms_p95": 0.0,
                    "t_preload_ms": 33.52
                }
            },
            "derived": {
                "drop_rate_fps": 14.4,
                "drop_count": 144,
                "window_sec": 10.0
            },
            "score": 24.67
        },
        {
            "timestamp": "2025-09-08 04:55:42",
            "window_sec": 10.0,
            "combination": "combination_9",
            "models": {
                "view1": {
                    "model": "resnet50_big",
                    "execution": "NPU0",
                    "throughput_fps": 19.82,
                    "avg_inference_time_ms": 50.46,
                    "inference_count": 91,
                    "avg_wait_to_preprocess_ms": 0.0,
                    "dropped_frames_due_to_full_queue": 0
                },
                "view2": {
                    "model": "resnet50_small",
                    "execution": "CPU",
                    "throughput_fps": 9.09,
                    "avg_inference_time_ms": 110.04,
                    "inference_count": 82,
                    "avg_wait_to_preprocess_ms": 0.0,
                    "dropped_frames_due_to_full_queue": 0
                },
                "view3": {
                    "model": "yolov3_small",
                    "execution": "NPU1",
                    "throughput_fps": 9.38,
                    "avg_inference_time_ms": 106.6,
                    "inference_count": 28,
                    "avg_wait_to_preprocess_ms": 1509.95,
                    "dropped_frames_due_to_full_queue": 80
                }
            },
            "total": {
                "total_throughput_fps": 38.29,
                "avg_throughput_fps": 12.76
            },
            "devices": {
                "cpu": {
                    "queue_wait_ms_p95": 0.0
                },
                "npu0": {
                    "queue_wait_ms_p95": 0.0,
                    "t_preload_ms": 33.52
                },
                "npu1": {
                    "queue_wait_ms_p95": 0.0,
                    "t_preload_ms": 464.87
                }
            },
            "derived": {
                "drop_rate_fps": 8.0,
                "drop_count": 80,
                "window_sec": 10.0
            },
            "score": 36.69
        }
    ]
}