{
    "best deployment": "combination_13",
    "schedule file": "exp_3_model_schedules_5.yaml",
    "data": [
        {
            "timestamp": "2025-09-04 09:31:26",
            "window_sec": 10.0,
            "combination": "combination_1",
            "models": {
                "view1": {
                    "model": "resnet50_small",
                    "execution": "CPU",
                    "throughput_fps": 7.89,
                    "avg_inference_time_ms": 126.69,
                    "inference_count": 75,
                    "avg_wait_to_preprocess_ms": 0.0,
                    "dropped_frames_due_to_full_queue": 0
                },
                "view2": {
                    "model": "yolov3_small",
                    "execution": "CPU",
                    "throughput_fps": 1.06,
                    "avg_inference_time_ms": 940.46,
                    "inference_count": 10,
                    "avg_wait_to_preprocess_ms": 5246.1,
                    "dropped_frames_due_to_full_queue": 257
                },
                "view3": {
                    "model": "yolov3_big",
                    "execution": "CPU",
                    "throughput_fps": 1.06,
                    "avg_inference_time_ms": 941.27,
                    "inference_count": 10,
                    "avg_wait_to_preprocess_ms": 5450.02,
                    "dropped_frames_due_to_full_queue": 257
                }
            },
            "total": {
                "total_throughput_fps": 10.02,
                "avg_throughput_fps": 3.34
            },
            "devices": {
                "cpu": {
                    "queue_wait_ms_p95": 5450.02
                }
            },
            "derived": {
                "drop_rate_fps": 51.4,
                "drop_count": 514,
                "window_sec": 10.0
            },
            "score": -0.26
        },
        {
            "timestamp": "2025-09-04 09:31:36",
            "window_sec": 10.0,
            "combination": "combination_10",
            "models": {
                "view1": {
                    "model": "resnet50_small",
                    "execution": "NPU0",
                    "throughput_fps": 18.78,
                    "avg_inference_time_ms": 53.26,
                    "inference_count": 95,
                    "avg_wait_to_preprocess_ms": 0.0,
                    "dropped_frames_due_to_full_queue": 0
                },
                "view2": {
                    "model": "yolov3_small",
                    "execution": "NPU1",
                    "throughput_fps": 11.72,
                    "avg_inference_time_ms": 85.31,
                    "inference_count": 38,
                    "avg_wait_to_preprocess_ms": 1168.11,
                    "dropped_frames_due_to_full_queue": 185
                },
                "view3": {
                    "model": "yolov3_big",
                    "execution": "CPU",
                    "throughput_fps": 2.33,
                    "avg_inference_time_ms": 429.72,
                    "inference_count": 20,
                    "avg_wait_to_preprocess_ms": 3555.45,
                    "dropped_frames_due_to_full_queue": 240
                }
            },
            "total": {
                "total_throughput_fps": 32.83,
                "avg_throughput_fps": 10.94
            },
            "devices": {
                "cpu": {
                    "queue_wait_ms_p95": 3555.45
                },
                "npu0": {
                    "queue_wait_ms_p95": 0.0,
                    "t_preload_ms": 33.52
                },
                "npu1": {
                    "queue_wait_ms_p95": 0.0,
                    "t_preload_ms": 464.87
                }
            },
            "derived": {
                "drop_rate_fps": 42.5,
                "drop_count": 425,
                "window_sec": 10.0
            },
            "score": 24.33
        },
        {
            "timestamp": "2025-09-04 09:31:48",
            "window_sec": 10.0,
            "combination": "combination_11",
            "models": {
                "view1": {
                    "model": "resnet50_small",
                    "execution": "NPU1",
                    "throughput_fps": 19.5,
                    "avg_inference_time_ms": 51.28,
                    "inference_count": 95,
                    "avg_wait_to_preprocess_ms": 0.0,
                    "dropped_frames_due_to_full_queue": 0
                },
                "view2": {
                    "model": "yolov3_small",
                    "execution": "CPU",
                    "throughput_fps": 1.7,
                    "avg_inference_time_ms": 587.19,
                    "inference_count": 15,
                    "avg_wait_to_preprocess_ms": 4398.87,
                    "dropped_frames_due_to_full_queue": 239
                },
                "view3": {
                    "model": "yolov3_big",
                    "execution": "CPU",
                    "throughput_fps": 1.71,
                    "avg_inference_time_ms": 585.73,
                    "inference_count": 15,
                    "avg_wait_to_preprocess_ms": 4462.55,
                    "dropped_frames_due_to_full_queue": 239
                }
            },
            "total": {
                "total_throughput_fps": 22.91,
                "avg_throughput_fps": 7.64
            },
            "devices": {
                "cpu": {
                    "queue_wait_ms_p95": 4462.55
                },
                "npu1": {
                    "queue_wait_ms_p95": 0.0,
                    "t_preload_ms": 464.87
                }
            },
            "derived": {
                "drop_rate_fps": 47.8,
                "drop_count": 478,
                "window_sec": 10.0
            },
            "score": 13.35
        },
        {
            "timestamp": "2025-09-04 09:31:58",
            "window_sec": 10.0,
            "combination": "combination_12",
            "models": {
                "view1": {
                    "model": "resnet50_small",
                    "execution": "NPU1",
                    "throughput_fps": 19.95,
                    "avg_inference_time_ms": 50.12,
                    "inference_count": 95,
                    "avg_wait_to_preprocess_ms": 0.0,
                    "dropped_frames_due_to_full_queue": 0
                },
                "view2": {
                    "model": "yolov3_small",
                    "execution": "CPU",
                    "throughput_fps": 2.47,
                    "avg_inference_time_ms": 404.7,
                    "inference_count": 21,
                    "avg_wait_to_preprocess_ms": 3459.66,
                    "dropped_frames_due_to_full_queue": 232
                },
                "view3": {
                    "model": "yolov3_big",
                    "execution": "NPU0",
                    "throughput_fps": 8.77,
                    "avg_inference_time_ms": 113.98,
                    "inference_count": 29,
                    "avg_wait_to_preprocess_ms": 1467.86,
                    "dropped_frames_due_to_full_queue": 195
                }
            },
            "total": {
                "total_throughput_fps": 31.2,
                "avg_throughput_fps": 10.4
            },
            "devices": {
                "cpu": {
                    "queue_wait_ms_p95": 3459.66
                },
                "npu0": {
                    "queue_wait_ms_p95": 0.0,
                    "t_preload_ms": 33.52
                },
                "npu1": {
                    "queue_wait_ms_p95": 0.0,
                    "t_preload_ms": 464.87
                }
            },
            "derived": {
                "drop_rate_fps": 42.7,
                "drop_count": 427,
                "window_sec": 10.0
            },
            "score": 22.66
        },
        {
            "timestamp": "2025-09-04 09:32:09",
            "window_sec": 10.0,
            "combination": "combination_13",
            "models": {
                "view1": {
                    "model": "resnet50_small",
                    "execution": "NPU1",
                    "throughput_fps": 20.17,
                    "avg_inference_time_ms": 49.58,
                    "inference_count": 95,
                    "avg_wait_to_preprocess_ms": 0.0,
                    "dropped_frames_due_to_full_queue": 0
                },
                "view2": {
                    "model": "yolov3_small",
                    "execution": "NPU0",
                    "throughput_fps": 11.85,
                    "avg_inference_time_ms": 84.36,
                    "inference_count": 38,
                    "avg_wait_to_preprocess_ms": 1142.59,
                    "dropped_frames_due_to_full_queue": 178
                },
                "view3": {
                    "model": "yolov3_big",
                    "execution": "CPU",
                    "throughput_fps": 1.97,
                    "avg_inference_time_ms": 507.32,
                    "inference_count": 17,
                    "avg_wait_to_preprocess_ms": 4026.52,
                    "dropped_frames_due_to_full_queue": 237
                }
            },
            "total": {
                "total_throughput_fps": 34.0,
                "avg_throughput_fps": 11.33
            },
            "devices": {
                "cpu": {
                    "queue_wait_ms_p95": 4026.52
                },
                "npu0": {
                    "queue_wait_ms_p95": 0.0,
                    "t_preload_ms": 33.52
                },
                "npu1": {
                    "queue_wait_ms_p95": 0.0,
                    "t_preload_ms": 464.87
                }
            },
            "derived": {
                "drop_rate_fps": 41.5,
                "drop_count": 415,
                "window_sec": 10.0
            },
            "score": 25.7
        },
        {
            "timestamp": "2025-09-04 09:32:20",
            "window_sec": 10.0,
            "combination": "combination_2",
            "models": {
                "view1": {
                    "model": "resnet50_small",
                    "execution": "CPU",
                    "throughput_fps": 6.84,
                    "avg_inference_time_ms": 146.24,
                    "inference_count": 62,
                    "avg_wait_to_preprocess_ms": 0.0,
                    "dropped_frames_due_to_full_queue": 0
                },
                "view2": {
                    "model": "yolov3_small",
                    "execution": "CPU",
                    "throughput_fps": 1.05,
                    "avg_inference_time_ms": 952.23,
                    "inference_count": 9,
                    "avg_wait_to_preprocess_ms": 4886.79,
                    "dropped_frames_due_to_full_queue": 239
                },
                "view3": {
                    "model": "yolov3_big",
                    "execution": "NPU0",
                    "throughput_fps": 7.57,
                    "avg_inference_time_ms": 132.18,
                    "inference_count": 24,
                    "avg_wait_to_preprocess_ms": 1754.7,
                    "dropped_frames_due_to_full_queue": 200
                }
            },
            "total": {
                "total_throughput_fps": 15.45,
                "avg_throughput_fps": 5.15
            },
            "devices": {
                "cpu": {
                    "queue_wait_ms_p95": 4886.79
                },
                "npu0": {
                    "queue_wait_ms_p95": 0.0,
                    "t_preload_ms": 33.52
                }
            },
            "derived": {
                "drop_rate_fps": 43.9,
                "drop_count": 439,
                "window_sec": 10.0
            },
            "score": 6.67
        },
        {
            "timestamp": "2025-09-04 09:32:31",
            "window_sec": 10.0,
            "combination": "combination_3",
            "models": {
                "view1": {
                    "model": "resnet50_small",
                    "execution": "CPU",
                    "throughput_fps": 7.22,
                    "avg_inference_time_ms": 138.43,
                    "inference_count": 65,
                    "avg_wait_to_preprocess_ms": 0.0,
                    "dropped_frames_due_to_full_queue": 0
                },
                "view2": {
                    "model": "yolov3_small",
                    "execution": "CPU",
                    "throughput_fps": 1.07,
                    "avg_inference_time_ms": 934.61,
                    "inference_count": 9,
                    "avg_wait_to_preprocess_ms": 5027.17,
                    "dropped_frames_due_to_full_queue": 237
                },
                "view3": {
                    "model": "yolov3_big",
                    "execution": "NPU1",
                    "throughput_fps": 7.07,
                    "avg_inference_time_ms": 141.36,
                    "inference_count": 22,
                    "avg_wait_to_preprocess_ms": 1921.71,
                    "dropped_frames_due_to_full_queue": 202
                }
            },
            "total": {
                "total_throughput_fps": 15.37,
                "avg_throughput_fps": 5.12
            },
            "devices": {
                "cpu": {
                    "queue_wait_ms_p95": 5027.17
                },
                "npu1": {
                    "queue_wait_ms_p95": 0.0,
                    "t_preload_ms": 464.87
                }
            },
            "derived": {
                "drop_rate_fps": 43.9,
                "drop_count": 439,
                "window_sec": 10.0
            },
            "score": 6.59
        },
        {
            "timestamp": "2025-09-04 09:32:43",
            "window_sec": 10.0,
            "combination": "combination_4",
            "models": {
                "view1": {
                    "model": "resnet50_small",
                    "execution": "CPU",
                    "throughput_fps": 6.67,
                    "avg_inference_time_ms": 149.89,
                    "inference_count": 61,
                    "avg_wait_to_preprocess_ms": 0.0,
                    "dropped_frames_due_to_full_queue": 0
                },
                "view2": {
                    "model": "yolov3_small",
                    "execution": "NPU0",
                    "throughput_fps": 9.36,
                    "avg_inference_time_ms": 106.88,
                    "inference_count": 30,
                    "avg_wait_to_preprocess_ms": 1422.33,
                    "dropped_frames_due_to_full_queue": 188
                },
                "view3": {
                    "model": "yolov3_big",
                    "execution": "CPU",
                    "throughput_fps": 1.05,
                    "avg_inference_time_ms": 954.62,
                    "inference_count": 9,
                    "avg_wait_to_preprocess_ms": 5130.89,
                    "dropped_frames_due_to_full_queue": 239
                }
            },
            "total": {
                "total_throughput_fps": 17.08,
                "avg_throughput_fps": 5.69
            },
            "devices": {
                "cpu": {
                    "queue_wait_ms_p95": 5130.89
                },
                "npu0": {
                    "queue_wait_ms_p95": 0.0,
                    "t_preload_ms": 33.52
                }
            },
            "derived": {
                "drop_rate_fps": 42.7,
                "drop_count": 427,
                "window_sec": 10.0
            },
            "score": 8.54
        },
        {
            "timestamp": "2025-09-04 09:32:53",
            "window_sec": 10.0,
            "combination": "combination_5",
            "models": {
                "view1": {
                    "model": "resnet50_small",
                    "execution": "CPU",
                    "throughput_fps": 7.63,
                    "avg_inference_time_ms": 131.12,
                    "inference_count": 69,
                    "avg_wait_to_preprocess_ms": 0.0,
                    "dropped_frames_due_to_full_queue": 0
                },
                "view2": {
                    "model": "yolov3_small",
                    "execution": "NPU0",
                    "throughput_fps": 10.62,
                    "avg_inference_time_ms": 94.18,
                    "inference_count": 32,
                    "avg_wait_to_preprocess_ms": 1353.33,
                    "dropped_frames_due_to_full_queue": 178
                },
                "view3": {
                    "model": "yolov3_big",
                    "execution": "NPU1",
                    "throughput_fps": 7.28,
                    "avg_inference_time_ms": 137.39,
                    "inference_count": 22,
                    "avg_wait_to_preprocess_ms": 1933.42,
                    "dropped_frames_due_to_full_queue": 199
                }
            },
            "total": {
                "total_throughput_fps": 25.52,
                "avg_throughput_fps": 8.51
            },
            "devices": {
                "cpu": {
                    "queue_wait_ms_p95": 0.0
                },
                "npu0": {
                    "queue_wait_ms_p95": 0.0,
                    "t_preload_ms": 33.52
                },
                "npu1": {
                    "queue_wait_ms_p95": 0.0,
                    "t_preload_ms": 464.87
                }
            },
            "derived": {
                "drop_rate_fps": 37.7,
                "drop_count": 377,
                "window_sec": 10.0
            },
            "score": 17.98
        },
        {
            "timestamp": "2025-09-04 09:33:04",
            "window_sec": 10.0,
            "combination": "combination_6",
            "models": {
                "view1": {
                    "model": "resnet50_small",
                    "execution": "CPU",
                    "throughput_fps": 5.65,
                    "avg_inference_time_ms": 176.86,
                    "inference_count": 51,
                    "avg_wait_to_preprocess_ms": 0.0,
                    "dropped_frames_due_to_full_queue": 0
                },
                "view2": {
                    "model": "yolov3_small",
                    "execution": "NPU1",
                    "throughput_fps": 8.47,
                    "avg_inference_time_ms": 118.05,
                    "inference_count": 24,
                    "avg_wait_to_preprocess_ms": 1775.39,
                    "dropped_frames_due_to_full_queue": 161
                },
                "view3": {
                    "model": "yolov3_big",
                    "execution": "CPU",
                    "throughput_fps": 1.07,
                    "avg_inference_time_ms": 935.16,
                    "inference_count": 9,
                    "avg_wait_to_preprocess_ms": 5004.76,
                    "dropped_frames_due_to_full_queue": 200
                }
            },
            "total": {
                "total_throughput_fps": 15.19,
                "avg_throughput_fps": 5.06
            },
            "devices": {
                "cpu": {
                    "queue_wait_ms_p95": 5004.76
                },
                "npu1": {
                    "queue_wait_ms_p95": 0.0,
                    "t_preload_ms": 464.87
                }
            },
            "derived": {
                "drop_rate_fps": 36.1,
                "drop_count": 361,
                "window_sec": 10.0
            },
            "score": 7.97
        },
        {
            "timestamp": "2025-09-04 09:33:15",
            "window_sec": 10.0,
            "combination": "combination_7",
            "models": {
                "view1": {
                    "model": "resnet50_small",
                    "execution": "CPU",
                    "throughput_fps": 8.07,
                    "avg_inference_time_ms": 123.86,
                    "inference_count": 74,
                    "avg_wait_to_preprocess_ms": 0.0,
                    "dropped_frames_due_to_full_queue": 0
                },
                "view2": {
                    "model": "yolov3_small",
                    "execution": "NPU1",
                    "throughput_fps": 9.65,
                    "avg_inference_time_ms": 103.59,
                    "inference_count": 29,
                    "avg_wait_to_preprocess_ms": 1480.12,
                    "dropped_frames_due_to_full_queue": 145
                },
                "view3": {
                    "model": "yolov3_big",
                    "execution": "NPU0",
                    "throughput_fps": 7.72,
                    "avg_inference_time_ms": 129.59,
                    "inference_count": 25,
                    "avg_wait_to_preprocess_ms": 1709.34,
                    "dropped_frames_due_to_full_queue": 154
                }
            },
            "total": {
                "total_throughput_fps": 25.44,
                "avg_throughput_fps": 8.48
            },
            "devices": {
                "cpu": {
                    "queue_wait_ms_p95": 0.0
                },
                "npu0": {
                    "queue_wait_ms_p95": 0.0,
                    "t_preload_ms": 33.52
                },
                "npu1": {
                    "queue_wait_ms_p95": 0.0,
                    "t_preload_ms": 464.87
                }
            },
            "derived": {
                "drop_rate_fps": 29.9,
                "drop_count": 299,
                "window_sec": 10.0
            },
            "score": 19.46
        },
        {
            "timestamp": "2025-09-04 09:33:26",
            "window_sec": 10.0,
            "combination": "combination_8",
            "models": {
                "view1": {
                    "model": "resnet50_small",
                    "execution": "NPU0",
                    "throughput_fps": 16.96,
                    "avg_inference_time_ms": 58.95,
                    "inference_count": 93,
                    "avg_wait_to_preprocess_ms": 0.0,
                    "dropped_frames_due_to_full_queue": 0
                },
                "view2": {
                    "model": "yolov3_small",
                    "execution": "CPU",
                    "throughput_fps": 1.56,
                    "avg_inference_time_ms": 641.34,
                    "inference_count": 13,
                    "avg_wait_to_preprocess_ms": 4618.47,
                    "dropped_frames_due_to_full_queue": 209
                },
                "view3": {
                    "model": "yolov3_big",
                    "execution": "CPU",
                    "throughput_fps": 1.45,
                    "avg_inference_time_ms": 688.8,
                    "inference_count": 12,
                    "avg_wait_to_preprocess_ms": 4775.5,
                    "dropped_frames_due_to_full_queue": 210
                }
            },
            "total": {
                "total_throughput_fps": 19.98,
                "avg_throughput_fps": 6.66
            },
            "devices": {
                "cpu": {
                    "queue_wait_ms_p95": 4775.5
                },
                "npu0": {
                    "queue_wait_ms_p95": 0.0,
                    "t_preload_ms": 33.52
                }
            },
            "derived": {
                "drop_rate_fps": 41.9,
                "drop_count": 419,
                "window_sec": 10.0
            },
            "score": 11.6
        },
        {
            "timestamp": "2025-09-04 09:33:37",
            "window_sec": 10.0,
            "combination": "combination_9",
            "models": {
                "view1": {
                    "model": "resnet50_small",
                    "execution": "NPU0",
                    "throughput_fps": 17.93,
                    "avg_inference_time_ms": 55.78,
                    "inference_count": 94,
                    "avg_wait_to_preprocess_ms": 0.0,
                    "dropped_frames_due_to_full_queue": 0
                },
                "view2": {
                    "model": "yolov3_small",
                    "execution": "CPU",
                    "throughput_fps": 2.15,
                    "avg_inference_time_ms": 465.44,
                    "inference_count": 18,
                    "avg_wait_to_preprocess_ms": 3846.03,
                    "dropped_frames_due_to_full_queue": 237
                },
                "view3": {
                    "model": "yolov3_big",
                    "execution": "NPU1",
                    "throughput_fps": 8.25,
                    "avg_inference_time_ms": 121.2,
                    "inference_count": 28,
                    "avg_wait_to_preprocess_ms": 1568.64,
                    "dropped_frames_due_to_full_queue": 200
                }
            },
            "total": {
                "total_throughput_fps": 28.33,
                "avg_throughput_fps": 9.44
            },
            "devices": {
                "cpu": {
                    "queue_wait_ms_p95": 3846.03
                },
                "npu0": {
                    "queue_wait_ms_p95": 0.0,
                    "t_preload_ms": 33.52
                },
                "npu1": {
                    "queue_wait_ms_p95": 0.0,
                    "t_preload_ms": 464.87
                }
            },
            "derived": {
                "drop_rate_fps": 43.7,
                "drop_count": 437,
                "window_sec": 10.0
            },
            "score": 19.59
        }
    ]
}