{
    "best deployment": "combination_9",
    "schedule file": "exp_4_model_schedules_1.yaml",
    "data": [
        {
            "timestamp": "2025-09-08 08:34:59",
            "window_sec": 10.0,
            "combination": "combination_1",
            "models": {
                "view1": {
                    "model": "resnet50_small",
                    "execution": "CPU",
                    "throughput_fps": 5.15,
                    "avg_inference_time_ms": 194.03,
                    "inference_count": 47,
                    "avg_wait_to_preprocess_ms": 0.0,
                    "dropped_frames_due_to_full_queue": 0
                },
                "view2": {
                    "model": "yolov3_small",
                    "execution": "CPU",
                    "throughput_fps": 0.71,
                    "avg_inference_time_ms": 1402.5,
                    "inference_count": 6,
                    "avg_wait_to_preprocess_ms": 4255.25,
                    "dropped_frames_due_to_full_queue": 239
                },
                "view3": {
                    "model": "yolov3_big",
                    "execution": "CPU",
                    "throughput_fps": 0.79,
                    "avg_inference_time_ms": 1266.66,
                    "inference_count": 6,
                    "avg_wait_to_preprocess_ms": 5488.25,
                    "dropped_frames_due_to_full_queue": 239
                },
                "view4": {
                    "model": "resnet50_big",
                    "execution": "CPU",
                    "throughput_fps": 3.54,
                    "avg_inference_time_ms": 282.72,
                    "inference_count": 20,
                    "avg_wait_to_preprocess_ms": 0.0,
                    "dropped_frames_due_to_full_queue": 0
                }
            },
            "total": {
                "total_throughput_fps": 10.19,
                "avg_throughput_fps": 2.55
            },
            "devices": {
                "cpu": {
                    "queue_wait_ms_p95": 5488.25
                }
            },
            "derived": {
                "drop_rate_fps": 47.8,
                "drop_count": 478,
                "window_sec": 10.0
            },
            "score": 0.63
        },
        {
            "timestamp": "2025-09-08 08:35:10",
            "window_sec": 10.0,
            "combination": "combination_10",
            "models": {
                "view1": {
                    "model": "resnet50_small",
                    "execution": "CPU",
                    "throughput_fps": 6.04,
                    "avg_inference_time_ms": 165.47,
                    "inference_count": 55,
                    "avg_wait_to_preprocess_ms": 0.0,
                    "dropped_frames_due_to_full_queue": 0
                },
                "view2": {
                    "model": "yolov3_small",
                    "execution": "NPU0",
                    "throughput_fps": 9.17,
                    "avg_inference_time_ms": 109.06,
                    "inference_count": 26,
                    "avg_wait_to_preprocess_ms": 1646.74,
                    "dropped_frames_due_to_full_queue": 198
                },
                "view3": {
                    "model": "yolov3_big",
                    "execution": "NPU1",
                    "throughput_fps": 7.56,
                    "avg_inference_time_ms": 132.29,
                    "inference_count": 24,
                    "avg_wait_to_preprocess_ms": 1763.81,
                    "dropped_frames_due_to_full_queue": 202
                },
                "view4": {
                    "model": "resnet50_big",
                    "execution": "CPU",
                    "throughput_fps": 3.91,
                    "avg_inference_time_ms": 255.57,
                    "inference_count": 20,
                    "avg_wait_to_preprocess_ms": 0.0,
                    "dropped_frames_due_to_full_queue": 0
                }
            },
            "total": {
                "total_throughput_fps": 26.68,
                "avg_throughput_fps": 6.67
            },
            "devices": {
                "npu0": {
                    "queue_wait_ms_p95": 0.0,
                    "t_preload_ms": 33.52
                },
                "cpu": {
                    "queue_wait_ms_p95": 0.0
                },
                "npu1": {
                    "queue_wait_ms_p95": 0.0,
                    "t_preload_ms": 464.87
                }
            },
            "derived": {
                "drop_rate_fps": 40.0,
                "drop_count": 400,
                "window_sec": 10.0
            },
            "score": 18.68
        },
        {
            "timestamp": "2025-09-08 08:35:22",
            "window_sec": 10.0,
            "combination": "combination_11",
            "models": {
                "view1": {
                    "model": "resnet50_small",
                    "execution": "CPU",
                    "throughput_fps": 5.57,
                    "avg_inference_time_ms": 179.48,
                    "inference_count": 50,
                    "avg_wait_to_preprocess_ms": 0.0,
                    "dropped_frames_due_to_full_queue": 0
                },
                "view2": {
                    "model": "yolov3_small",
                    "execution": "NPU1",
                    "throughput_fps": 8.45,
                    "avg_inference_time_ms": 118.34,
                    "inference_count": 23,
                    "avg_wait_to_preprocess_ms": 1831.41,
                    "dropped_frames_due_to_full_queue": 196
                },
                "view3": {
                    "model": "yolov3_big",
                    "execution": "CPU",
                    "throughput_fps": 0.77,
                    "avg_inference_time_ms": 1300.45,
                    "inference_count": 6,
                    "avg_wait_to_preprocess_ms": 5496.38,
                    "dropped_frames_due_to_full_queue": 236
                },
                "view4": {
                    "model": "resnet50_big",
                    "execution": "CPU",
                    "throughput_fps": 3.54,
                    "avg_inference_time_ms": 282.22,
                    "inference_count": 20,
                    "avg_wait_to_preprocess_ms": 0.0,
                    "dropped_frames_due_to_full_queue": 0
                }
            },
            "total": {
                "total_throughput_fps": 18.33,
                "avg_throughput_fps": 4.58
            },
            "devices": {
                "cpu": {
                    "queue_wait_ms_p95": 5496.38
                },
                "npu1": {
                    "queue_wait_ms_p95": 0.0,
                    "t_preload_ms": 464.87
                }
            },
            "derived": {
                "drop_rate_fps": 43.2,
                "drop_count": 432,
                "window_sec": 10.0
            },
            "score": 9.69
        },
        {
            "timestamp": "2025-09-08 08:35:32",
            "window_sec": 10.0,
            "combination": "combination_12",
            "models": {
                "view1": {
                    "model": "resnet50_small",
                    "execution": "CPU",
                    "throughput_fps": 6.14,
                    "avg_inference_time_ms": 162.82,
                    "inference_count": 56,
                    "avg_wait_to_preprocess_ms": 0.0,
                    "dropped_frames_due_to_full_queue": 0
                },
                "view2": {
                    "model": "yolov3_small",
                    "execution": "NPU1",
                    "throughput_fps": 8.8,
                    "avg_inference_time_ms": 113.59,
                    "inference_count": 24,
                    "avg_wait_to_preprocess_ms": 1812.3,
                    "dropped_frames_due_to_full_queue": 200
                },
                "view3": {
                    "model": "yolov3_big",
                    "execution": "CPU",
                    "throughput_fps": 0.97,
                    "avg_inference_time_ms": 1026.52,
                    "inference_count": 8,
                    "avg_wait_to_preprocess_ms": 4705.69,
                    "dropped_frames_due_to_full_queue": 238
                },
                "view4": {
                    "model": "resnet50_big",
                    "execution": "NPU0",
                    "throughput_fps": 19.69,
                    "avg_inference_time_ms": 50.79,
                    "inference_count": 20,
                    "avg_wait_to_preprocess_ms": 0.0,
                    "dropped_frames_due_to_full_queue": 0
                }
            },
            "total": {
                "total_throughput_fps": 35.61,
                "avg_throughput_fps": 8.9
            },
            "devices": {
                "npu0": {
                    "queue_wait_ms_p95": 0.0,
                    "t_preload_ms": 33.52
                },
                "cpu": {
                    "queue_wait_ms_p95": 4705.69
                },
                "npu1": {
                    "queue_wait_ms_p95": 0.0,
                    "t_preload_ms": 464.87
                }
            },
            "derived": {
                "drop_rate_fps": 43.8,
                "drop_count": 438,
                "window_sec": 10.0
            },
            "score": 26.85
        },
        {
            "timestamp": "2025-09-08 08:35:43",
            "window_sec": 10.0,
            "combination": "combination_13",
            "models": {
                "view1": {
                    "model": "resnet50_small",
                    "execution": "CPU",
                    "throughput_fps": 5.19,
                    "avg_inference_time_ms": 192.68,
                    "inference_count": 47,
                    "avg_wait_to_preprocess_ms": 0.0,
                    "dropped_frames_due_to_full_queue": 0
                },
                "view2": {
                    "model": "yolov3_small",
                    "execution": "NPU1",
                    "throughput_fps": 8.44,
                    "avg_inference_time_ms": 118.47,
                    "inference_count": 25,
                    "avg_wait_to_preprocess_ms": 1699.35,
                    "dropped_frames_due_to_full_queue": 193
                },
                "view3": {
                    "model": "yolov3_big",
                    "execution": "NPU0",
                    "throughput_fps": 7.18,
                    "avg_inference_time_ms": 139.33,
                    "inference_count": 23,
                    "avg_wait_to_preprocess_ms": 1864.2,
                    "dropped_frames_due_to_full_queue": 198
                },
                "view4": {
                    "model": "resnet50_big",
                    "execution": "CPU",
                    "throughput_fps": 3.5,
                    "avg_inference_time_ms": 285.68,
                    "inference_count": 20,
                    "avg_wait_to_preprocess_ms": 0.0,
                    "dropped_frames_due_to_full_queue": 0
                }
            },
            "total": {
                "total_throughput_fps": 24.31,
                "avg_throughput_fps": 6.08
            },
            "devices": {
                "npu0": {
                    "queue_wait_ms_p95": 0.0,
                    "t_preload_ms": 33.52
                },
                "cpu": {
                    "queue_wait_ms_p95": 0.0
                },
                "npu1": {
                    "queue_wait_ms_p95": 0.0,
                    "t_preload_ms": 464.87
                }
            },
            "derived": {
                "drop_rate_fps": 39.1,
                "drop_count": 391,
                "window_sec": 10.0
            },
            "score": 16.49
        },
        {
            "timestamp": "2025-09-08 08:35:55",
            "window_sec": 10.0,
            "combination": "combination_14",
            "models": {
                "view1": {
                    "model": "resnet50_small",
                    "execution": "NPU0",
                    "throughput_fps": 17.9,
                    "avg_inference_time_ms": 55.88,
                    "inference_count": 20,
                    "avg_wait_to_preprocess_ms": 0.0,
                    "dropped_frames_due_to_full_queue": 0
                },
                "view2": {
                    "model": "yolov3_small",
                    "execution": "CPU",
                    "throughput_fps": 1.19,
                    "avg_inference_time_ms": 839.48,
                    "inference_count": 10,
                    "avg_wait_to_preprocess_ms": 4746.54,
                    "dropped_frames_due_to_full_queue": 235
                },
                "view3": {
                    "model": "yolov3_big",
                    "execution": "CPU",
                    "throughput_fps": 1.09,
                    "avg_inference_time_ms": 915.15,
                    "inference_count": 9,
                    "avg_wait_to_preprocess_ms": 4735.24,
                    "dropped_frames_due_to_full_queue": 236
                },
                "view4": {
                    "model": "resnet50_big",
                    "execution": "CPU",
                    "throughput_fps": 4.51,
                    "avg_inference_time_ms": 221.5,
                    "inference_count": 20,
                    "avg_wait_to_preprocess_ms": 0.0,
                    "dropped_frames_due_to_full_queue": 0
                }
            },
            "total": {
                "total_throughput_fps": 24.69,
                "avg_throughput_fps": 6.17
            },
            "devices": {
                "npu0": {
                    "queue_wait_ms_p95": 0.0,
                    "t_preload_ms": 33.52
                },
                "cpu": {
                    "queue_wait_ms_p95": 4746.54
                }
            },
            "derived": {
                "drop_rate_fps": 47.1,
                "drop_count": 471,
                "window_sec": 10.0
            },
            "score": 15.27
        },
        {
            "timestamp": "2025-09-08 08:36:05",
            "window_sec": 10.0,
            "combination": "combination_15",
            "models": {
                "view1": {
                    "model": "resnet50_small",
                    "execution": "NPU0",
                    "throughput_fps": 18.09,
                    "avg_inference_time_ms": 55.28,
                    "inference_count": 20,
                    "avg_wait_to_preprocess_ms": 0.0,
                    "dropped_frames_due_to_full_queue": 0
                },
                "view2": {
                    "model": "yolov3_small",
                    "execution": "CPU",
                    "throughput_fps": 1.44,
                    "avg_inference_time_ms": 693.35,
                    "inference_count": 12,
                    "avg_wait_to_preprocess_ms": 4649.61,
                    "dropped_frames_due_to_full_queue": 238
                },
                "view3": {
                    "model": "yolov3_big",
                    "execution": "CPU",
                    "throughput_fps": 1.68,
                    "avg_inference_time_ms": 595.77,
                    "inference_count": 14,
                    "avg_wait_to_preprocess_ms": 4517.81,
                    "dropped_frames_due_to_full_queue": 236
                },
                "view4": {
                    "model": "resnet50_big",
                    "execution": "NPU1",
                    "throughput_fps": 19.04,
                    "avg_inference_time_ms": 52.52,
                    "inference_count": 20,
                    "avg_wait_to_preprocess_ms": 0.0,
                    "dropped_frames_due_to_full_queue": 0
                }
            },
            "total": {
                "total_throughput_fps": 40.25,
                "avg_throughput_fps": 10.06
            },
            "devices": {
                "npu0": {
                    "queue_wait_ms_p95": 0.0,
                    "t_preload_ms": 33.52
                },
                "cpu": {
                    "queue_wait_ms_p95": 4649.61
                },
                "npu1": {
                    "queue_wait_ms_p95": 0.0,
                    "t_preload_ms": 464.87
                }
            },
            "derived": {
                "drop_rate_fps": 47.4,
                "drop_count": 474,
                "window_sec": 10.0
            },
            "score": 30.77
        },
        {
            "timestamp": "2025-09-08 08:36:16",
            "window_sec": 10.0,
            "combination": "combination_16",
            "models": {
                "view1": {
                    "model": "resnet50_small",
                    "execution": "NPU0",
                    "throughput_fps": 17.15,
                    "avg_inference_time_ms": 58.31,
                    "inference_count": 20,
                    "avg_wait_to_preprocess_ms": 0.0,
                    "dropped_frames_due_to_full_queue": 0
                },
                "view2": {
                    "model": "yolov3_small",
                    "execution": "CPU",
                    "throughput_fps": 1.58,
                    "avg_inference_time_ms": 634.08,
                    "inference_count": 13,
                    "avg_wait_to_preprocess_ms": 4467.94,
                    "dropped_frames_due_to_full_queue": 236
                },
                "view3": {
                    "model": "yolov3_big",
                    "execution": "NPU1",
                    "throughput_fps": 7.42,
                    "avg_inference_time_ms": 134.86,
                    "inference_count": 22,
                    "avg_wait_to_preprocess_ms": 1909.16,
                    "dropped_frames_due_to_full_queue": 205
                },
                "view4": {
                    "model": "resnet50_big",
                    "execution": "CPU",
                    "throughput_fps": 4.87,
                    "avg_inference_time_ms": 205.51,
                    "inference_count": 20,
                    "avg_wait_to_preprocess_ms": 0.0,
                    "dropped_frames_due_to_full_queue": 0
                }
            },
            "total": {
                "total_throughput_fps": 31.01,
                "avg_throughput_fps": 7.75
            },
            "devices": {
                "npu0": {
                    "queue_wait_ms_p95": 0.0,
                    "t_preload_ms": 33.52
                },
                "cpu": {
                    "queue_wait_ms_p95": 4467.94
                },
                "npu1": {
                    "queue_wait_ms_p95": 0.0,
                    "t_preload_ms": 464.87
                }
            },
            "derived": {
                "drop_rate_fps": 44.1,
                "drop_count": 441,
                "window_sec": 10.0
            },
            "score": 22.19
        },
        {
            "timestamp": "2025-09-08 08:36:29",
            "window_sec": 10.0,
            "combination": "combination_17",
            "models": {
                "view1": {
                    "model": "resnet50_small",
                    "execution": "NPU0",
                    "throughput_fps": 17.13,
                    "avg_inference_time_ms": 58.39,
                    "inference_count": 22,
                    "avg_wait_to_preprocess_ms": 0.0,
                    "dropped_frames_due_to_full_queue": 0
                },
                "view2": {
                    "model": "yolov3_small",
                    "execution": "NPU1",
                    "throughput_fps": 8.53,
                    "avg_inference_time_ms": 117.24,
                    "inference_count": 29,
                    "avg_wait_to_preprocess_ms": 1595.25,
                    "dropped_frames_due_to_full_queue": 206
                },
                "view3": {
                    "model": "yolov3_big",
                    "execution": "CPU",
                    "throughput_fps": 1.5,
                    "avg_inference_time_ms": 667.39,
                    "inference_count": 14,
                    "avg_wait_to_preprocess_ms": 4710.66,
                    "dropped_frames_due_to_full_queue": 250
                },
                "view4": {
                    "model": "resnet50_big",
                    "execution": "CPU",
                    "throughput_fps": 4.58,
                    "avg_inference_time_ms": 218.18,
                    "inference_count": 22,
                    "avg_wait_to_preprocess_ms": 0.0,
                    "dropped_frames_due_to_full_queue": 0
                }
            },
            "total": {
                "total_throughput_fps": 31.74,
                "avg_throughput_fps": 7.93
            },
            "devices": {
                "npu0": {
                    "queue_wait_ms_p95": 0.0,
                    "t_preload_ms": 33.52
                },
                "cpu": {
                    "queue_wait_ms_p95": 4710.66
                },
                "npu1": {
                    "queue_wait_ms_p95": 0.0,
                    "t_preload_ms": 464.87
                }
            },
            "derived": {
                "drop_rate_fps": 45.6,
                "drop_count": 456,
                "window_sec": 10.0
            },
            "score": 22.62
        },
        {
            "timestamp": "2025-09-08 08:36:40",
            "window_sec": 10.0,
            "combination": "combination_18",
            "models": {
                "view1": {
                    "model": "resnet50_small",
                    "execution": "NPU1",
                    "throughput_fps": 20.18,
                    "avg_inference_time_ms": 49.56,
                    "inference_count": 21,
                    "avg_wait_to_preprocess_ms": 0.0,
                    "dropped_frames_due_to_full_queue": 0
                },
                "view2": {
                    "model": "yolov3_small",
                    "execution": "CPU",
                    "throughput_fps": 1.04,
                    "avg_inference_time_ms": 958.75,
                    "inference_count": 9,
                    "avg_wait_to_preprocess_ms": 4993.76,
                    "dropped_frames_due_to_full_queue": 217
                },
                "view3": {
                    "model": "yolov3_big",
                    "execution": "CPU",
                    "throughput_fps": 1.03,
                    "avg_inference_time_ms": 968.24,
                    "inference_count": 9,
                    "avg_wait_to_preprocess_ms": 5252.97,
                    "dropped_frames_due_to_full_queue": 217
                },
                "view4": {
                    "model": "resnet50_big",
                    "execution": "CPU",
                    "throughput_fps": 3.98,
                    "avg_inference_time_ms": 251.27,
                    "inference_count": 21,
                    "avg_wait_to_preprocess_ms": 0.0,
                    "dropped_frames_due_to_full_queue": 0
                }
            },
            "total": {
                "total_throughput_fps": 26.23,
                "avg_throughput_fps": 6.56
            },
            "devices": {
                "cpu": {
                    "queue_wait_ms_p95": 5252.97
                },
                "npu1": {
                    "queue_wait_ms_p95": 0.0,
                    "t_preload_ms": 464.87
                }
            },
            "derived": {
                "drop_rate_fps": 43.4,
                "drop_count": 434,
                "window_sec": 10.0
            },
            "score": 17.55
        },
        {
            "timestamp": "2025-09-08 08:36:51",
            "window_sec": 10.0,
            "combination": "combination_19",
            "models": {
                "view1": {
                    "model": "resnet50_small",
                    "execution": "NPU1",
                    "throughput_fps": 19.26,
                    "avg_inference_time_ms": 51.91,
                    "inference_count": 22,
                    "avg_wait_to_preprocess_ms": 0.0,
                    "dropped_frames_due_to_full_queue": 0
                },
                "view2": {
                    "model": "yolov3_small",
                    "execution": "CPU",
                    "throughput_fps": 1.35,
                    "avg_inference_time_ms": 743.09,
                    "inference_count": 12,
                    "avg_wait_to_preprocess_ms": 5335.7,
                    "dropped_frames_due_to_full_queue": 212
                },
                "view3": {
                    "model": "yolov3_big",
                    "execution": "CPU",
                    "throughput_fps": 1.55,
                    "avg_inference_time_ms": 643.7,
                    "inference_count": 14,
                    "avg_wait_to_preprocess_ms": 4751.99,
                    "dropped_frames_due_to_full_queue": 210
                },
                "view4": {
                    "model": "resnet50_big",
                    "execution": "NPU0",
                    "throughput_fps": 16.5,
                    "avg_inference_time_ms": 60.62,
                    "inference_count": 22,
                    "avg_wait_to_preprocess_ms": 0.0,
                    "dropped_frames_due_to_full_queue": 0
                }
            },
            "total": {
                "total_throughput_fps": 38.66,
                "avg_throughput_fps": 9.66
            },
            "devices": {
                "npu0": {
                    "queue_wait_ms_p95": 0.0,
                    "t_preload_ms": 33.52
                },
                "cpu": {
                    "queue_wait_ms_p95": 5335.7
                },
                "npu1": {
                    "queue_wait_ms_p95": 0.0,
                    "t_preload_ms": 464.87
                }
            },
            "derived": {
                "drop_rate_fps": 42.2,
                "drop_count": 422,
                "window_sec": 10.0
            },
            "score": 30.22
        },
        {
            "timestamp": "2025-09-08 08:37:03",
            "window_sec": 10.0,
            "combination": "combination_2",
            "models": {
                "view1": {
                    "model": "resnet50_small",
                    "execution": "CPU",
                    "throughput_fps": 5.97,
                    "avg_inference_time_ms": 167.62,
                    "inference_count": 58,
                    "avg_wait_to_preprocess_ms": 0.0,
                    "dropped_frames_due_to_full_queue": 0
                },
                "view2": {
                    "model": "yolov3_small",
                    "execution": "CPU",
                    "throughput_fps": 0.78,
                    "avg_inference_time_ms": 1288.7,
                    "inference_count": 7,
                    "avg_wait_to_preprocess_ms": 5393.3,
                    "dropped_frames_due_to_full_queue": 126
                },
                "view3": {
                    "model": "yolov3_big",
                    "execution": "CPU",
                    "throughput_fps": 0.76,
                    "avg_inference_time_ms": 1311.28,
                    "inference_count": 6,
                    "avg_wait_to_preprocess_ms": 5996.33,
                    "dropped_frames_due_to_full_queue": 127
                },
                "view4": {
                    "model": "resnet50_big",
                    "execution": "NPU0",
                    "throughput_fps": 17.71,
                    "avg_inference_time_ms": 56.47,
                    "inference_count": 21,
                    "avg_wait_to_preprocess_ms": 0.0,
                    "dropped_frames_due_to_full_queue": 0
                }
            },
            "total": {
                "total_throughput_fps": 25.21,
                "avg_throughput_fps": 6.3
            },
            "devices": {
                "npu0": {
                    "queue_wait_ms_p95": 0.0,
                    "t_preload_ms": 33.52
                },
                "cpu": {
                    "queue_wait_ms_p95": 5996.33
                }
            },
            "derived": {
                "drop_rate_fps": 25.3,
                "drop_count": 253,
                "window_sec": 10.0
            },
            "score": 20.15
        },
        {
            "timestamp": "2025-09-08 08:37:15",
            "window_sec": 10.0,
            "combination": "combination_20",
            "models": {
                "view1": {
                    "model": "resnet50_small",
                    "execution": "NPU1",
                    "throughput_fps": 19.63,
                    "avg_inference_time_ms": 50.95,
                    "inference_count": 22,
                    "avg_wait_to_preprocess_ms": 0.0,
                    "dropped_frames_due_to_full_queue": 0
                },
                "view2": {
                    "model": "yolov3_small",
                    "execution": "CPU",
                    "throughput_fps": 1.5,
                    "avg_inference_time_ms": 667.7,
                    "inference_count": 14,
                    "avg_wait_to_preprocess_ms": 4926.69,
                    "dropped_frames_due_to_full_queue": 158
                },
                "view3": {
                    "model": "yolov3_big",
                    "execution": "NPU0",
                    "throughput_fps": 7.64,
                    "avg_inference_time_ms": 130.92,
                    "inference_count": 28,
                    "avg_wait_to_preprocess_ms": 1651.8,
                    "dropped_frames_due_to_full_queue": 116
                },
                "view4": {
                    "model": "resnet50_big",
                    "execution": "CPU",
                    "throughput_fps": 4.68,
                    "avg_inference_time_ms": 213.46,
                    "inference_count": 22,
                    "avg_wait_to_preprocess_ms": 0.0,
                    "dropped_frames_due_to_full_queue": 0
                }
            },
            "total": {
                "total_throughput_fps": 33.45,
                "avg_throughput_fps": 8.36
            },
            "devices": {
                "npu0": {
                    "queue_wait_ms_p95": 0.0,
                    "t_preload_ms": 33.52
                },
                "cpu": {
                    "queue_wait_ms_p95": 4926.69
                },
                "npu1": {
                    "queue_wait_ms_p95": 0.0,
                    "t_preload_ms": 464.87
                }
            },
            "derived": {
                "drop_rate_fps": 27.4,
                "drop_count": 274,
                "window_sec": 10.0
            },
            "score": 27.97
        },
        {
            "timestamp": "2025-09-08 08:37:27",
            "window_sec": 10.0,
            "combination": "combination_21",
            "models": {
                "view1": {
                    "model": "resnet50_small",
                    "execution": "NPU1",
                    "throughput_fps": 19.13,
                    "avg_inference_time_ms": 52.27,
                    "inference_count": 22,
                    "avg_wait_to_preprocess_ms": 0.0,
                    "dropped_frames_due_to_full_queue": 0
                },
                "view2": {
                    "model": "yolov3_small",
                    "execution": "NPU0",
                    "throughput_fps": 9.18,
                    "avg_inference_time_ms": 108.93,
                    "inference_count": 31,
                    "avg_wait_to_preprocess_ms": 1509.11,
                    "dropped_frames_due_to_full_queue": 86
                },
                "view3": {
                    "model": "yolov3_big",
                    "execution": "CPU",
                    "throughput_fps": 1.31,
                    "avg_inference_time_ms": 764.34,
                    "inference_count": 12,
                    "avg_wait_to_preprocess_ms": 5235.41,
                    "dropped_frames_due_to_full_queue": 136
                },
                "view4": {
                    "model": "resnet50_big",
                    "execution": "CPU",
                    "throughput_fps": 4.8,
                    "avg_inference_time_ms": 208.39,
                    "inference_count": 22,
                    "avg_wait_to_preprocess_ms": 0.0,
                    "dropped_frames_due_to_full_queue": 0
                }
            },
            "total": {
                "total_throughput_fps": 34.42,
                "avg_throughput_fps": 8.6
            },
            "devices": {
                "npu0": {
                    "queue_wait_ms_p95": 0.0,
                    "t_preload_ms": 33.52
                },
                "cpu": {
                    "queue_wait_ms_p95": 5235.41
                },
                "npu1": {
                    "queue_wait_ms_p95": 0.0,
                    "t_preload_ms": 464.87
                }
            },
            "derived": {
                "drop_rate_fps": 22.2,
                "drop_count": 222,
                "window_sec": 10.0
            },
            "score": 29.98
        },
        {
            "timestamp": "2025-09-08 08:37:39",
            "window_sec": 10.0,
            "combination": "combination_3",
            "models": {
                "view1": {
                    "model": "resnet50_small",
                    "execution": "CPU",
                    "throughput_fps": 5.63,
                    "avg_inference_time_ms": 177.64,
                    "inference_count": 56,
                    "avg_wait_to_preprocess_ms": 0.0,
                    "dropped_frames_due_to_full_queue": 0
                },
                "view2": {
                    "model": "yolov3_small",
                    "execution": "CPU",
                    "throughput_fps": 0.89,
                    "avg_inference_time_ms": 1118.87,
                    "inference_count": 8,
                    "avg_wait_to_preprocess_ms": 5620.34,
                    "dropped_frames_due_to_full_queue": 101
                },
                "view3": {
                    "model": "yolov3_big",
                    "execution": "CPU",
                    "throughput_fps": 0.86,
                    "avg_inference_time_ms": 1157.56,
                    "inference_count": 8,
                    "avg_wait_to_preprocess_ms": 5302.16,
                    "dropped_frames_due_to_full_queue": 101
                },
                "view4": {
                    "model": "resnet50_big",
                    "execution": "NPU1",
                    "throughput_fps": 18.88,
                    "avg_inference_time_ms": 52.98,
                    "inference_count": 22,
                    "avg_wait_to_preprocess_ms": 0.0,
                    "dropped_frames_due_to_full_queue": 0
                }
            },
            "total": {
                "total_throughput_fps": 26.26,
                "avg_throughput_fps": 6.57
            },
            "devices": {
                "cpu": {
                    "queue_wait_ms_p95": 5620.34
                },
                "npu1": {
                    "queue_wait_ms_p95": 0.0,
                    "t_preload_ms": 464.87
                }
            },
            "derived": {
                "drop_rate_fps": 20.2,
                "drop_count": 202,
                "window_sec": 10.0
            },
            "score": 22.22
        },
        {
            "timestamp": "2025-09-08 08:37:50",
            "window_sec": 10.0,
            "combination": "combination_4",
            "models": {
                "view1": {
                    "model": "resnet50_small",
                    "execution": "CPU",
                    "throughput_fps": 3.86,
                    "avg_inference_time_ms": 258.91,
                    "inference_count": 36,
                    "avg_wait_to_preprocess_ms": 0.0,
                    "dropped_frames_due_to_full_queue": 0
                },
                "view2": {
                    "model": "yolov3_small",
                    "execution": "CPU",
                    "throughput_fps": 0.6,
                    "avg_inference_time_ms": 1677.67,
                    "inference_count": 5,
                    "avg_wait_to_preprocess_ms": 4938.57,
                    "dropped_frames_due_to_full_queue": 87
                },
                "view3": {
                    "model": "yolov3_big",
                    "execution": "NPU0",
                    "throughput_fps": 7.49,
                    "avg_inference_time_ms": 133.47,
                    "inference_count": 22,
                    "avg_wait_to_preprocess_ms": 1948.53,
                    "dropped_frames_due_to_full_queue": 49
                },
                "view4": {
                    "model": "resnet50_big",
                    "execution": "CPU",
                    "throughput_fps": 2.72,
                    "avg_inference_time_ms": 368.12,
                    "inference_count": 20,
                    "avg_wait_to_preprocess_ms": 0.0,
                    "dropped_frames_due_to_full_queue": 0
                }
            },
            "total": {
                "total_throughput_fps": 14.67,
                "avg_throughput_fps": 3.67
            },
            "devices": {
                "npu0": {
                    "queue_wait_ms_p95": 0.0,
                    "t_preload_ms": 33.52
                },
                "cpu": {
                    "queue_wait_ms_p95": 4938.57
                }
            },
            "derived": {
                "drop_rate_fps": 13.6,
                "drop_count": 136,
                "window_sec": 10.0
            },
            "score": 11.95
        },
        {
            "timestamp": "2025-09-08 08:38:02",
            "window_sec": 10.0,
            "combination": "combination_5",
            "models": {
                "view1": {
                    "model": "resnet50_small",
                    "execution": "CPU",
                    "throughput_fps": 5.38,
                    "avg_inference_time_ms": 185.89,
                    "inference_count": 54,
                    "avg_wait_to_preprocess_ms": 0.0,
                    "dropped_frames_due_to_full_queue": 0
                },
                "view2": {
                    "model": "yolov3_small",
                    "execution": "CPU",
                    "throughput_fps": 0.79,
                    "avg_inference_time_ms": 1264.04,
                    "inference_count": 7,
                    "avg_wait_to_preprocess_ms": 5043.39,
                    "dropped_frames_due_to_full_queue": 68
                },
                "view3": {
                    "model": "yolov3_big",
                    "execution": "NPU0",
                    "throughput_fps": 7.45,
                    "avg_inference_time_ms": 134.23,
                    "inference_count": 26,
                    "avg_wait_to_preprocess_ms": 1662.41,
                    "dropped_frames_due_to_full_queue": 24
                },
                "view4": {
                    "model": "resnet50_big",
                    "execution": "NPU1",
                    "throughput_fps": 18.96,
                    "avg_inference_time_ms": 52.76,
                    "inference_count": 22,
                    "avg_wait_to_preprocess_ms": 0.0,
                    "dropped_frames_due_to_full_queue": 0
                }
            },
            "total": {
                "total_throughput_fps": 32.58,
                "avg_throughput_fps": 8.14
            },
            "devices": {
                "npu0": {
                    "queue_wait_ms_p95": 0.0,
                    "t_preload_ms": 33.52
                },
                "cpu": {
                    "queue_wait_ms_p95": 5043.39
                },
                "npu1": {
                    "queue_wait_ms_p95": 0.0,
                    "t_preload_ms": 464.87
                }
            },
            "derived": {
                "drop_rate_fps": 9.2,
                "drop_count": 92,
                "window_sec": 10.0
            },
            "score": 30.74
        },
        {
            "timestamp": "2025-09-08 08:38:14",
            "window_sec": 10.0,
            "combination": "combination_6",
            "models": {
                "view1": {
                    "model": "resnet50_small",
                    "execution": "CPU",
                    "throughput_fps": 4.52,
                    "avg_inference_time_ms": 221.05,
                    "inference_count": 45,
                    "avg_wait_to_preprocess_ms": 0.0,
                    "dropped_frames_due_to_full_queue": 0
                },
                "view2": {
                    "model": "yolov3_small",
                    "execution": "CPU",
                    "throughput_fps": 0.55,
                    "avg_inference_time_ms": 1804.08,
                    "inference_count": 5,
                    "avg_wait_to_preprocess_ms": 5129.11,
                    "dropped_frames_due_to_full_queue": 63
                },
                "view3": {
                    "model": "yolov3_big",
                    "execution": "NPU1",
                    "throughput_fps": 6.77,
                    "avg_inference_time_ms": 147.64,
                    "inference_count": 22,
                    "avg_wait_to_preprocess_ms": 1952.19,
                    "dropped_frames_due_to_full_queue": 24
                },
                "view4": {
                    "model": "resnet50_big",
                    "execution": "CPU",
                    "throughput_fps": 3.44,
                    "avg_inference_time_ms": 291.01,
                    "inference_count": 21,
                    "avg_wait_to_preprocess_ms": 0.0,
                    "dropped_frames_due_to_full_queue": 0
                }
            },
            "total": {
                "total_throughput_fps": 15.29,
                "avg_throughput_fps": 3.82
            },
            "devices": {
                "cpu": {
                    "queue_wait_ms_p95": 5129.11
                },
                "npu1": {
                    "queue_wait_ms_p95": 0.0,
                    "t_preload_ms": 464.87
                }
            },
            "derived": {
                "drop_rate_fps": 8.7,
                "drop_count": 87,
                "window_sec": 10.0
            },
            "score": 13.55
        },
        {
            "timestamp": "2025-09-08 08:38:26",
            "window_sec": 10.0,
            "combination": "combination_7",
            "models": {
                "view1": {
                    "model": "resnet50_small",
                    "execution": "CPU",
                    "throughput_fps": 6.04,
                    "avg_inference_time_ms": 165.48,
                    "inference_count": 60,
                    "avg_wait_to_preprocess_ms": 0.0,
                    "dropped_frames_due_to_full_queue": 0
                },
                "view2": {
                    "model": "yolov3_small",
                    "execution": "CPU",
                    "throughput_fps": 1.01,
                    "avg_inference_time_ms": 993.79,
                    "inference_count": 9,
                    "avg_wait_to_preprocess_ms": 5194.41,
                    "dropped_frames_due_to_full_queue": 56
                },
                "view3": {
                    "model": "yolov3_big",
                    "execution": "NPU1",
                    "throughput_fps": 6.63,
                    "avg_inference_time_ms": 150.94,
                    "inference_count": 21,
                    "avg_wait_to_preprocess_ms": 2093.91,
                    "dropped_frames_due_to_full_queue": 24
                },
                "view4": {
                    "model": "resnet50_big",
                    "execution": "NPU0",
                    "throughput_fps": 17.28,
                    "avg_inference_time_ms": 57.86,
                    "inference_count": 22,
                    "avg_wait_to_preprocess_ms": 0.0,
                    "dropped_frames_due_to_full_queue": 0
                }
            },
            "total": {
                "total_throughput_fps": 30.96,
                "avg_throughput_fps": 7.74
            },
            "devices": {
                "npu0": {
                    "queue_wait_ms_p95": 0.0,
                    "t_preload_ms": 33.52
                },
                "cpu": {
                    "queue_wait_ms_p95": 5194.41
                },
                "npu1": {
                    "queue_wait_ms_p95": 0.0,
                    "t_preload_ms": 464.87
                }
            },
            "derived": {
                "drop_rate_fps": 8.0,
                "drop_count": 80,
                "window_sec": 10.0
            },
            "score": 29.36
        },
        {
            "timestamp": "2025-09-08 08:38:38",
            "window_sec": 10.0,
            "combination": "combination_8",
            "models": {
                "view1": {
                    "model": "resnet50_small",
                    "execution": "CPU",
                    "throughput_fps": 4.86,
                    "avg_inference_time_ms": 205.82,
                    "inference_count": 48,
                    "avg_wait_to_preprocess_ms": 0.0,
                    "dropped_frames_due_to_full_queue": 0
                },
                "view2": {
                    "model": "yolov3_small",
                    "execution": "NPU0",
                    "throughput_fps": 9.19,
                    "avg_inference_time_ms": 108.83,
                    "inference_count": 22,
                    "avg_wait_to_preprocess_ms": 1167.97,
                    "dropped_frames_due_to_full_queue": 15
                },
                "view3": {
                    "model": "yolov3_big",
                    "execution": "CPU",
                    "throughput_fps": 0.64,
                    "avg_inference_time_ms": 1569.47,
                    "inference_count": 5,
                    "avg_wait_to_preprocess_ms": 5334.5,
                    "dropped_frames_due_to_full_queue": 54
                },
                "view4": {
                    "model": "resnet50_big",
                    "execution": "CPU",
                    "throughput_fps": 3.44,
                    "avg_inference_time_ms": 290.76,
                    "inference_count": 21,
                    "avg_wait_to_preprocess_ms": 0.0,
                    "dropped_frames_due_to_full_queue": 0
                }
            },
            "total": {
                "total_throughput_fps": 18.12,
                "avg_throughput_fps": 4.53
            },
            "devices": {
                "npu0": {
                    "queue_wait_ms_p95": 0.0,
                    "t_preload_ms": 33.52
                },
                "cpu": {
                    "queue_wait_ms_p95": 5334.5
                }
            },
            "derived": {
                "drop_rate_fps": 6.9,
                "drop_count": 69,
                "window_sec": 10.0
            },
            "score": 16.74
        },
        {
            "timestamp": "2025-09-08 08:38:50",
            "window_sec": 10.0,
            "combination": "combination_9",
            "models": {
                "view1": {
                    "model": "resnet50_small",
                    "execution": "CPU",
                    "throughput_fps": 6.11,
                    "avg_inference_time_ms": 163.63,
                    "inference_count": 61,
                    "avg_wait_to_preprocess_ms": 0.0,
                    "dropped_frames_due_to_full_queue": 0
                },
                "view2": {
                    "model": "yolov3_small",
                    "execution": "NPU0",
                    "throughput_fps": 8.86,
                    "avg_inference_time_ms": 112.81,
                    "inference_count": 22,
                    "avg_wait_to_preprocess_ms": 1063.9,
                    "dropped_frames_due_to_full_queue": 5
                },
                "view3": {
                    "model": "yolov3_big",
                    "execution": "CPU",
                    "throughput_fps": 0.93,
                    "avg_inference_time_ms": 1074.87,
                    "inference_count": 8,
                    "avg_wait_to_preprocess_ms": 5379.77,
                    "dropped_frames_due_to_full_queue": 40
                },
                "view4": {
                    "model": "resnet50_big",
                    "execution": "NPU1",
                    "throughput_fps": 16.85,
                    "avg_inference_time_ms": 59.34,
                    "inference_count": 21,
                    "avg_wait_to_preprocess_ms": 0.0,
                    "dropped_frames_due_to_full_queue": 0
                }
            },
            "total": {
                "total_throughput_fps": 32.76,
                "avg_throughput_fps": 8.19
            },
            "devices": {
                "npu0": {
                    "queue_wait_ms_p95": 0.0,
                    "t_preload_ms": 33.52
                },
                "cpu": {
                    "queue_wait_ms_p95": 5379.77
                },
                "npu1": {
                    "queue_wait_ms_p95": 0.0,
                    "t_preload_ms": 464.87
                }
            },
            "derived": {
                "drop_rate_fps": 4.5,
                "drop_count": 45,
                "window_sec": 10.0
            },
            "score": 31.86
        }
    ]
}