{
    "best deployment": "combination_7",
    "schedule file": "model_schedules_2model_yb_ys_2.yaml",
    "data": [
        {
            "timestamp": "2025-09-08 04:40:43",
            "window_sec": 10.0,
            "combination": "combination_1",
            "models": {
                "view1": {
                    "model": "yolov3_big",
                    "execution": "CPU",
                    "throughput_fps": 2.15,
                    "avg_inference_time_ms": 465.48,
                    "inference_count": 18,
                    "avg_wait_to_preprocess_ms": 3718.9,
                    "dropped_frames_due_to_full_queue": 225
                },
                "view2": {
                    "model": "yolov3_small",
                    "execution": "CPU",
                    "throughput_fps": 2.13,
                    "avg_inference_time_ms": 469.52,
                    "inference_count": 18,
                    "avg_wait_to_preprocess_ms": 3851.68,
                    "dropped_frames_due_to_full_queue": 227
                }
            },
            "total": {
                "total_throughput_fps": 4.28,
                "avg_throughput_fps": 2.14
            },
            "devices": {
                "cpu": {
                    "queue_wait_ms_p95": 3851.68
                }
            },
            "derived": {
                "drop_rate_fps": 45.2,
                "drop_count": 452,
                "window_sec": 10.0
            },
            "score": -4.76
        },
        {
            "timestamp": "2025-09-08 04:40:54",
            "window_sec": 10.0,
            "combination": "combination_2",
            "models": {
                "view1": {
                    "model": "yolov3_big",
                    "execution": "CPU",
                    "throughput_fps": 3.01,
                    "avg_inference_time_ms": 331.94,
                    "inference_count": 26,
                    "avg_wait_to_preprocess_ms": 2880.36,
                    "dropped_frames_due_to_full_queue": 216
                },
                "view2": {
                    "model": "yolov3_small",
                    "execution": "NPU0",
                    "throughput_fps": 12.11,
                    "avg_inference_time_ms": 82.59,
                    "inference_count": 41,
                    "avg_wait_to_preprocess_ms": 1080.04,
                    "dropped_frames_due_to_full_queue": 123
                }
            },
            "total": {
                "total_throughput_fps": 15.12,
                "avg_throughput_fps": 7.56
            },
            "devices": {
                "npu0": {
                    "queue_wait_ms_p95": 0.0,
                    "t_preload_ms": 33.52
                },
                "cpu": {
                    "queue_wait_ms_p95": 2880.36
                }
            },
            "derived": {
                "drop_rate_fps": 33.9,
                "drop_count": 339,
                "window_sec": 10.0
            },
            "score": 8.34
        },
        {
            "timestamp": "2025-09-08 04:41:05",
            "window_sec": 10.0,
            "combination": "combination_3",
            "models": {
                "view1": {
                    "model": "yolov3_big",
                    "execution": "CPU",
                    "throughput_fps": 3.23,
                    "avg_inference_time_ms": 309.18,
                    "inference_count": 28,
                    "avg_wait_to_preprocess_ms": 2809.99,
                    "dropped_frames_due_to_full_queue": 214
                },
                "view2": {
                    "model": "yolov3_small",
                    "execution": "NPU1",
                    "throughput_fps": 11.27,
                    "avg_inference_time_ms": 88.76,
                    "inference_count": 37,
                    "avg_wait_to_preprocess_ms": 1185.32,
                    "dropped_frames_due_to_full_queue": 140
                }
            },
            "total": {
                "total_throughput_fps": 14.5,
                "avg_throughput_fps": 7.25
            },
            "devices": {
                "npu1": {
                    "queue_wait_ms_p95": 0.0,
                    "t_preload_ms": 464.87
                },
                "cpu": {
                    "queue_wait_ms_p95": 2809.99
                }
            },
            "derived": {
                "drop_rate_fps": 35.4,
                "drop_count": 354,
                "window_sec": 10.0
            },
            "score": 7.42
        },
        {
            "timestamp": "2025-09-08 04:41:16",
            "window_sec": 10.0,
            "combination": "combination_4",
            "models": {
                "view1": {
                    "model": "yolov3_big",
                    "execution": "NPU0",
                    "throughput_fps": 9.3,
                    "avg_inference_time_ms": 107.55,
                    "inference_count": 33,
                    "avg_wait_to_preprocess_ms": 1339.69,
                    "dropped_frames_due_to_full_queue": 160
                },
                "view2": {
                    "model": "yolov3_small",
                    "execution": "CPU",
                    "throughput_fps": 3.44,
                    "avg_inference_time_ms": 290.97,
                    "inference_count": 29,
                    "avg_wait_to_preprocess_ms": 2617.0,
                    "dropped_frames_due_to_full_queue": 212
                }
            },
            "total": {
                "total_throughput_fps": 12.73,
                "avg_throughput_fps": 6.37
            },
            "devices": {
                "npu0": {
                    "queue_wait_ms_p95": 0.0,
                    "t_preload_ms": 33.52
                },
                "cpu": {
                    "queue_wait_ms_p95": 2617.0
                }
            },
            "derived": {
                "drop_rate_fps": 37.2,
                "drop_count": 372,
                "window_sec": 10.0
            },
            "score": 5.29
        },
        {
            "timestamp": "2025-09-08 04:41:27",
            "window_sec": 10.0,
            "combination": "combination_5",
            "models": {
                "view1": {
                    "model": "yolov3_big",
                    "execution": "NPU0",
                    "throughput_fps": 0.0,
                    "avg_inference_time_ms": 0.0,
                    "inference_count": 0,
                    "avg_wait_to_preprocess_ms": 0.0,
                    "dropped_frames_due_to_full_queue": 268
                },
                "view2": {
                    "model": "yolov3_small",
                    "execution": "NPU1",
                    "throughput_fps": 13.25,
                    "avg_inference_time_ms": 75.47,
                    "inference_count": 46,
                    "avg_wait_to_preprocess_ms": 959.13,
                    "dropped_frames_due_to_full_queue": 127
                }
            },
            "total": {
                "total_throughput_fps": 13.25,
                "avg_throughput_fps": 6.62
            },
            "devices": {
                "npu0": {
                    "queue_wait_ms_p95": 0.0,
                    "t_preload_ms": 33.52
                },
                "npu1": {
                    "queue_wait_ms_p95": 0.0,
                    "t_preload_ms": 464.87
                }
            },
            "derived": {
                "drop_rate_fps": 39.5,
                "drop_count": 395,
                "window_sec": 10.0
            },
            "score": 5.35
        },
        {
            "timestamp": "2025-09-08 04:41:38",
            "window_sec": 10.0,
            "combination": "combination_6",
            "models": {
                "view1": {
                    "model": "yolov3_big",
                    "execution": "NPU1",
                    "throughput_fps": 8.75,
                    "avg_inference_time_ms": 114.26,
                    "inference_count": 30,
                    "avg_wait_to_preprocess_ms": 1449.35,
                    "dropped_frames_due_to_full_queue": 180
                },
                "view2": {
                    "model": "yolov3_small",
                    "execution": "CPU",
                    "throughput_fps": 3.86,
                    "avg_inference_time_ms": 259.07,
                    "inference_count": 33,
                    "avg_wait_to_preprocess_ms": 2377.61,
                    "dropped_frames_due_to_full_queue": 212
                }
            },
            "total": {
                "total_throughput_fps": 12.61,
                "avg_throughput_fps": 6.31
            },
            "devices": {
                "npu1": {
                    "queue_wait_ms_p95": 0.0,
                    "t_preload_ms": 464.87
                },
                "cpu": {
                    "queue_wait_ms_p95": 2377.61
                }
            },
            "derived": {
                "drop_rate_fps": 39.2,
                "drop_count": 392,
                "window_sec": 10.0
            },
            "score": 4.77
        },
        {
            "timestamp": "2025-09-08 04:41:49",
            "window_sec": 10.0,
            "combination": "combination_7",
            "models": {
                "view1": {
                    "model": "yolov3_big",
                    "execution": "NPU1",
                    "throughput_fps": 9.46,
                    "avg_inference_time_ms": 105.66,
                    "inference_count": 34,
                    "avg_wait_to_preprocess_ms": 1294.86,
                    "dropped_frames_due_to_full_queue": 169
                },
                "view2": {
                    "model": "yolov3_small",
                    "execution": "NPU0",
                    "throughput_fps": 14.32,
                    "avg_inference_time_ms": 69.83,
                    "inference_count": 50,
                    "avg_wait_to_preprocess_ms": 880.87,
                    "dropped_frames_due_to_full_queue": 128
                }
            },
            "total": {
                "total_throughput_fps": 23.78,
                "avg_throughput_fps": 11.89
            },
            "devices": {
                "npu0": {
                    "queue_wait_ms_p95": 0.0,
                    "t_preload_ms": 33.52
                },
                "npu1": {
                    "queue_wait_ms_p95": 0.0,
                    "t_preload_ms": 464.87
                }
            },
            "derived": {
                "drop_rate_fps": 29.7,
                "drop_count": 297,
                "window_sec": 10.0
            },
            "score": 17.84
        }
    ]
}